gpg_chat/__init__.py
gpg_chat/app.css
gpg_chat/client.py
gpg_chat/main.py
gpg_chat/core/paths.py
gpg_chat/encryption/gpg_service.py
gpg_chat/encryption/utils.py
gpg_chat-0.2.1.dist-info/METADATA
gpg_chat-0.2.1.dist-info/WHEEL
gpg_chat-0.2.1.dist-info/entry_points.txt
gpg_chat-0.2.1.dist-info/RECORD
