Metadata-Version: 2.4
Name: gpg-chat
Version: 0.2.1
Summary: A terminal GPG chat built with Textual
Author-email: Alecsandre Antoine <diabeul@live.fr>
Keywords: python
Requires-Python: >=3.10
Requires-Dist: asyncio>=3.4.3
Requires-Dist: click<8.2.0
Requires-Dist: easygui>=0.98.3
Requires-Dist: pyperclip>=1.9.0
Requires-Dist: textual>=3.3.0
Requires-Dist: typer>=0.16.0
